asyncari/__init__.py
asyncari/client.py
asyncari/model.py
asyncari/state.py
asyncari/util.py
asyncari-0.20.5.dist-info/licenses/LICENSE
asyncari-0.20.5.dist-info/licenses/LICENSE.APACHE2
asyncari-0.20.5.dist-info/licenses/LICENSE.MIT
asyncari-0.20.5.dist-info/METADATA
asyncari-0.20.5.dist-info/WHEEL
asyncari-0.20.5.dist-info/top_level.txt
asyncari-0.20.5.dist-info/RECORD
